h3ppy/__init__.py
h3ppy/h2.py
h3ppy/h3p.py
h3ppy/data/h2_line_list_roueff_2019_subset.txt
h3ppy/data/h3p_line_list_neale_1996_subset.txt
h3ppy-0.6.1.dist-info/LICENSE
h3ppy-0.6.1.dist-info/METADATA
h3ppy-0.6.1.dist-info/WHEEL
h3ppy-0.6.1.dist-info/top_level.txt
h3ppy-0.6.1.dist-info/RECORD
