Metadata-Version: 2.2
Name: h3ppy
Version: 0.6.1
Summary: Model and fit H3+ spectra
Home-page: https://github.com/henrikmelin/h3ppy
Author: Henrik Melin
Author-email: h.melin@gmail.com
Keywords: infrared spectroscopy H3+ modelling
Classifier: Operating System :: POSIX :: Linux
Classifier: License :: OSI Approved :: MIT License
Classifier: Programming Language :: Python :: 3.5
Classifier: Programming Language :: Python :: 3.6
Classifier: Programming Language :: Python :: 3.7
License-File: LICENSE
Requires-Dist: numpy
Dynamic: author
Dynamic: author-email
Dynamic: classifier
Dynamic: description
Dynamic: description-content-type
Dynamic: home-page
Dynamic: keywords
Dynamic: requires-dist
Dynamic: summary
